{
	"dataAdmin": "Администратор данных",
	"dataManager": "Управление данными",
	"eth-american-indiannative-americanindigenous-person": "Американское индейское/коренное население",
	"eth-asian": "Азия",
	"eth-biracialmultiracial": "Бирасиальная многорасовая",
	"eth-black": "Черный",
	"eth-latinoaxhispanic": "Латино/a/x/Hispanic",
	"eth-middle-easternnorth-african": "Ближний Восток/Северная Африка",
	"eth-native-hawaiianpacific-islander": "Нативный гавайский/тихоокеанский остров",
	"eth-other": "Прочие вопросы",
	"eth-prefer-not-to-say": "Предпочитаю не говорить",
	"eth-south-asian": "Южная Азия",
	"eth-white": "Белый",
	"identity-ally": "Питомник",
	"identity-asexual": "Асексуал",
	"identity-bisexual": "Бисексуал",
	"identity-gay": "Гей",
	"identity-intersex": "Интерсекс",
	"identity-lesbian": "Lesbian",
	"identity-man": "Человек",
	"identity-nonbinary": "Недвоичный",
	"identity-pansexual": "Pansexual",
	"identity-queer": "Queer",
	"identity-questioning": "Вопросы",
	"identity-straight": "Прямой",
	"identity-transgender": "Транспол",
	"identity-woman": "Женская",
	"immigration-asylee": "Асыле (предоставленное убежище)",
	"immigration-asylum-seeker": "Искатель убежища",
	"immigration-dreamer": "Dreamer (получатель DACA)",
	"immigration-immigrant": "Иммигрант",
	"immigration-refugee": "Беженцы",
	"lcr": "Просмотр локального сообщества",
	"provider": "Поставщик услуг",
	"seeker": "Искатель ресурсов",
	"sysadmin": "Системный администратор",
	"type-dataadmin": "Администратор данных",
	"type-datamanager": "Управление данными",
	"type-lcr": "Просмотр локального сообщества",
	"type-provider": "Поставщик услуг",
	"type-seeker": "Искатель ресурсов",
	"type-sysadmin": "Системный администратор",
	"type-system": "Системный пользователь"
}