{
	"about-us": "crwdns8100:0crwdne8100:0",
	"contact-us": "crwdns8106:0crwdne8106:0",
	"edit-profile": "crwdns362182:0crwdne362182:0",
	"inreach": "crwdns362184:0crwdne362184:0",
	"log-in": "crwdns362186:0crwdne362186:0",
	"log-out": "crwdns362188:0crwdne362188:0",
	"questions": "crwdns8104:0crwdne8104:0",
	"saved-lists": "crwdns362190:0crwdne362190:0",
	"settings": "crwdns362192:0crwdne362192:0",
	"sign-up": "crwdns362194:0crwdne362194:0",
	"take-action": "crwdns8102:0crwdne8102:0",
	"user-avatar": "crwdns362196:0crwdne362196:0",
	"your-comments": "crwdns362198:0crwdne362198:0",
	"safety-exit": "crwdns790312:0crwdne790312:0"
}